catcatch/__init__.py
catcatch-0.1.dist-info/METADATA
catcatch-0.1.dist-info/WHEEL
catcatch-0.1.dist-info/top_level.txt
catcatch-0.1.dist-info/RECORD
