Metadata-Version: 2.1
Name: catcatch
Version: 0.1
Summary: try/except with exception name.
Home-page: https://github.com/uid613/catcatch
Author: Anton Teplykh
Author-email: wowitsnotcute@gmail.com
License: UNKNOWN
Download-URL: https://github.com/uid613/catcatch/talball/0.1
Keywords: try,except,decorator,catch,catcatch,exceptions,exception,error,errors
Platform: UNKNOWN
